sales_reporter/__init__.py
sales_reporter/__main__.py
sales_reporter/report_manager.py
sales_reporter_kolya_star-0.1.1.dist-info/METADATA
sales_reporter_kolya_star-0.1.1.dist-info/WHEEL
sales_reporter_kolya_star-0.1.1.dist-info/entry_points.txt
sales_reporter_kolya_star-0.1.1.dist-info/top_level.txt
sales_reporter_kolya_star-0.1.1.dist-info/RECORD
