Metadata-Version: 2.1
Name: sales_reporter_kolya_star
Version: 0.1.1
Summary: Пакет для отчета по продажам
Author-email: Nikolai <kolaleuhin@gmail.com>
Requires-Dist: pandas
